FlavorBuilder/__init__.py
FlavorBuilder/Model2Mass/Model2Mass.py
FlavorBuilder/Model2Mass/__init__.py
FlavorBuilder/PyDiscrete/PyDiscrete.py
FlavorBuilder/PyDiscrete/__init__.py
FlavorBuilder/PyDiscrete/saved_groups.pkl
FlavorBuilder/PyDiscrete/GAP-Script/extractGroupDataPy.gap
flavorbuilder-0.3.1.dist-info/licenses/LICENSE
flavorbuilder-0.3.1.dist-info/METADATA
flavorbuilder-0.3.1.dist-info/WHEEL
flavorbuilder-0.3.1.dist-info/top_level.txt
flavorbuilder-0.3.1.dist-info/RECORD
