Metadata-Version: 2.4
Name: FlavorBuilder
Version: 0.3.1
Summary: Finite-group and model-building utilities interfacing with GAP
Author-email: Victoria Knapp Pérez <vknapppe@uci.edu>, Jake Rudolph <jirudolp@uci.edu>
License: MIT License
Project-URL: Homepage, https://github.com/victoria-kp/FlavorBuilder
Project-URL: Repository, https://github.com/victoria-kp/FlavorBuilder
Project-URL: Issues, https://github.com/victoria-kp/FlavorBuilder
Keywords: particle-physics,group-theory,flavor-models,GAP,symmetry,mass-matrices,beyond-standard-model,physics,Amber
Classifier: Programming Language :: Python :: 3
Classifier: License :: OSI Approved :: MIT License
Classifier: Operating System :: OS Independent
Classifier: Intended Audience :: Science/Research
Classifier: Topic :: Scientific/Engineering :: Physics
Requires-Python: >=3.9
License-File: LICENSE
Requires-Dist: numpy
Requires-Dist: sympy
Requires-Dist: pandas
Provides-Extra: notebook
Requires-Dist: IPython; extra == "notebook"
Dynamic: license-file
